{
    "Per Kivijärvi": 0,
    "William Laahanen": 0,
    "Johannes Karlsson": 0,
    "Adam Laahanen": 0,
    "Filip Lidhammar": 0,
    "Jennifer Johansson": 0,
    "Lukas Frösslund": 0,
    "Albin Thurén": 0,
    "William Magnusson": 0,
    "Hugo Arvidsson": 0,
    "Erik Gustafsson": 0,
    "Robert Lidhammar": 0,
    "Cajsa Eriksson": 0,
    "Patric Hjorth": 0,
    "Jacob Hjorth": 0,
    "Andreas Eriksson": 0,
    "Valdemar Gezelius": 0,
    "Viktor Hansson": 0,
    "Isabella Johannesson": 0,
    "Pontus Lundgren": 0,
    "Anton Wårdell": 0,
    "Oscar Andersson": 0, 
    "David Berg": 0,
    "Kenneth Runnman": 0,
    "Sebastian Brånemark": 0,
    "Ted Karlsson": 0,
    "Linnéa Amundson": 0,
    "Alexander Jarlenäs": 0,
    "Andreas Schill": 0,
    "Hedvig Fahlstedt": 0,
    "Patricia Correia": 0,
    "Adam de Lancey": 0,
    "Amanda Nilsson": 0,
    "Tor Simmons": 0,
    "Alicia Brånemark": 0,
    "Filip Mälberg": 0,
    "Noel Milleskog": 0,
    "Hanna Milleskog": 0,
    "Jonny Frösslund": 0
}